chronomancy/__init__.py
chronomancy/arcane_recall.py
chronomancy/previous_frame.py
Chronomancy-0.0.2.dist-info/LICENSE
Chronomancy-0.0.2.dist-info/METADATA
Chronomancy-0.0.2.dist-info/WHEEL
Chronomancy-0.0.2.dist-info/top_level.txt
Chronomancy-0.0.2.dist-info/RECORD
