Metadata-Version: 2.1
Name: Chronomancy
Version: 0.0.2
Summary: The power of Time itself, for Python
Home-page: https://github.com/IAmTheBlurr/Chronomancy
Author: Jonathan Craig
Author-email: blurr@iamtheblurr.com
License: MIT
Platform: UNKNOWN
Classifier: Intended Audience :: Developers
Classifier: License :: OSI Approved :: MIT License
Classifier: Operating System :: MacOS
Classifier: Operating System :: Microsoft :: Windows
Classifier: Operating System :: POSIX :: Linux
Classifier: Programming Language :: Python :: 3.7
Classifier: Topic :: Software Development :: Libraries :: Python Modules
